{
  "iteration": 15,
  "timestamp": "2026-05-12T02:31:56.035542+00:00",
  "subspaces": [
    {
      "start": 0,
      "end": 10,
      "active": 8,
      "attempt": 1
    },
    {
      "start": 10,
      "end": 20,
      "active": 4,
      "attempt": 1
    },
    {
      "start": 20,
      "end": 30,
      "active": 4,
      "attempt": 1
    },
    {
      "start": 30,
      "end": 40,
      "active": 7,
      "attempt": 1
    },
    {
      "start": 40,
      "end": 50,
      "active": 4,
      "attempt": 1
    },
    {
      "start": 50,
      "end": 60,
      "active": 5,
      "attempt": 1
    },
    {
      "start": 60,
      "end": 70,
      "active": 6,
      "attempt": 1
    },
    {
      "start": 70,
      "end": 80,
      "active": 6,
      "attempt": 1
    },
    {
      "start": 80,
      "end": 90,
      "active": 5,
      "attempt": 1
    },
    {
      "start": 90,
      "end": 100,
      "active": 8,
      "attempt": 1
    },
    {
      "start": 100,
      "end": 110,
      "active": 5,
      "attempt": 1
    },
    {
      "start": 110,
      "end": 120,
      "active": 5,
      "attempt": 1
    }
  ],
  "outer_round": 0,
  "energy": 36.12347909197481,
  "best_energy": 31.56344110911349,
  "active_edges": 60
}